{
  "required": true,
  "package": "archives.tater.rpgskills.mixin",
  "compatibilityLevel": "JAVA_17",
  "mixins": [
    "advancement.ItemStackMixin",
    "advancement.PlayerEntityMixin",
    "advancement.SlotMixin",
    "attribute.BowItemMixin",
    "attribute.CrossbowItemMixin",
    "attribute.LivingEntityMixin",
    "compat.brewinandchewin.KegMenuMixin",
    "compat.cataclysm.WeaponFusionMenuMixin",
    "compat.chipped.WorkbenchMenuMixin",
    "compat.penchant.PenchantmentMenuMixin",
    "compat.spellengine.SpellHelperMixin",
    "job.AbstractCriterionMixin",
    "job.AdvancementCriterionAccessor",
    "locking.AnvilScreenHandlerMixin",
    "locking.BoatItemAccessor",
    "locking.CraftingScreenHandlerMixin",
    "locking.ItemStackMixin",
    "locking.LivingEntityMixin",
    "locking.ServerPlayerInteractionManagerMixin",
    "locking.SmithingScreenHandlerMixin",
    "scaling.LivingEntityMixin",
    "scaling.MobEntityMixin",
    "scaling.PlayerEntityMixin",
    "xp.AdvancementRewardsMixin",
    "xp.AnimalEntityMixin",
    "xp.ExperienceDroppingBlockMixin",
    "xp.FishingBobberEntityMixin",
    "xp.LivingEntityMixin",
    "xp.MobEntityMixin",
    "xp.MobSpawnerLogicMixin",
    "xp.RedstoneOreBlockMixin"
  ],
  "injectors": {
    "defaultRequire": 1
	}
}
