{
  "required": true,
  "package": "archives.tater.rpgskills.mixin.client",
  "compatibilityLevel": "JAVA_17",
  "client": [
    "xp.ClientPlayNetworkHandlerMixin",
    "locking.CraftingScreenMixin",
    "locking.HandledScreenAccessor",
    "xp.InGameHudMixin",
    "locking.InventoryScreenMixin",
    "locking.MinecraftClientMixin",
    "locking.ScreenAccessor",
    "compat.bettercombat.WeaponAttributeTooltipMixin"
  ],
  "injectors": {
    "defaultRequire": 1
  },
  "plugin": "archives.tater.rpgskills.client.RPGSkillsMixinConfigPlugin"
}
